{
  "S010": "S010 使用者基本数据维护",
  "S020": "S020 群组基本数据维护",
  "S030": "S030 程序基本数据维护",
  "S040": "S040 群组使用者数据维护",
  "S050": "S050 依群组设定程序使用权",
  "S060": "S060 依使用者设定程序使用权",
  "S070": "S070 代码维护(Not apply不适用)",
  "S080": "S080 使用者登入密码变更",
  "S090": "S090 翻译字典维护",
  "P020": "P020 交货单分配库存出库(自动)",
  "P030": "P030 交货单分配库存出库(人工)",
  "P060": "P060 转储出库",
  "P070": "P070 托盘库存调整",
  "P080": "P080 库存移转",
  "P090": "P090 空托盘码垛",
  "P100": "P100 空托盘出库",
  "M070": "M070 AS/RS搬运命令维护",
  "M090": "M090 n库位使用状态维护",
  "C010": "C010 自动仓库存盘点",
  "C030": "C030 盘点数据记录",
  "C040": "C040 盘点差异调整",
  "Q010": "Q010 库存产品基本数据查询",
  "Q020": "Q020 产品替代包装单位基本数据查询",
  "Q030": "Q030 储存载具基本数据查询",
  "Q040": "Q040 移转需求数据查询",
  "Q050": "Q050 交货单数据查询",
  "Q060": "Q060 盘点单数据查询",
  "Q070": "Q070 自动仓搬运命令查询",
  "Q080": "Q080 库存数据查询",
  "Q090": "Q090 库位使用状态查询",
  "Q100": "Q100 库位状态查询",
  "Q110": "Q110 转储记录数据查询",
  "Q120": "Q120 库存属性移转查询",
  "R030": "R030 上架日报",
  "R040": "R040 下架日报",
  "R050": "R050 库存查询报表",
  "R060": "R060 库存异动托盘数",
  "R070": "R070 库存异动交易数",
  "R080": "R080 盘点差异"
}
